pgcsv/__init__.py
pgcsv/cli.py
pgcsv/csv.py
pgcsv/db.py
pgcsv/util.py
pgcsv-0.4.dist-info/METADATA
pgcsv-0.4.dist-info/RECORD
pgcsv-0.4.dist-info/WHEEL
pgcsv-0.4.dist-info/entry_points.txt
pgcsv-0.4.dist-info/namespace_packages.txt
pgcsv-0.4.dist-info/top_level.txt
