Metadata-Version: 2.1
Name: pgcsv
Version: 0.4
Summary: CSV to Postgres data puncher.
Home-page: http://github.com/pudo/pgcsv
Author: Friedrich Lindenberh
Author-email: friedrich@pudo.org
License: MIT
Keywords: files walk index survey
Platform: UNKNOWN
Classifier: Development Status :: 3 - Alpha
Classifier: Intended Audience :: Developers
Classifier: License :: OSI Approved :: MIT License
Classifier: Operating System :: OS Independent
Classifier: Programming Language :: Python :: 2.6
Classifier: Programming Language :: Python :: 2.7
Classifier: Programming Language :: Python :: 3.7
Requires-Dist: six
Requires-Dist: click
Requires-Dist: psycopg2-binary (>=2.7)
Requires-Dist: backports.csv
Requires-Dist: normality
Requires-Dist: tabulate
